{"title":"Komen","body":[{"type":"p","text":"The conjugation of the present tense of komen (to come) is perfectly regular, it is just the stem that is irregular:"},{"type":"p","text":"Simple present:"},{"type":"table","table":[["ik","kom","we","komen"],["je","komt","jullie","komen"],["hij","komt","ze","komen"]]},{"type":"p","text":"Simple past:"},{"type":"table","table":[["ik","kwam","we","kwamen"],["je","kwam","jullie","kwamen"],["hij","kwam","ze","kwamen"]]},{"type":"p","text":"Past participle: gekomen"},{"type":"p","text":"Can you see the irregularity?"},{"type":"p","text":"Recall the first stem rule: a long vowel infinitive requires a long vowel stem. At least, this is what goes for regular verbs. In the case of the long-vowel-verb komen, we would expect the stem to be koom. But instead, we have a short-vowel-stem kom."},{"type":"p","text":"A few examples of verbs with the same conjugation as 'komen': 'bekomen' (to recover), 'ontkomen' (to escape), 'overkomen' (to happen to), 'aankomen' (to arrive, to put on weight)."}]}