{"title":"Compound nouns","body":[{"type":"p","text":"A compound noun is a noun that is made up of two or more words that can also occur independently, e.g. bed + room = bedroom."},{"type":"p","text":"the last word of the compound determines the overall gender of the compound noun"},{"type":"p","text":"In other words: Whether a compound noun is a de- or het-noun is determined by the last word in the compound."},{"type":"p","text":"The compound noun can consist of two independent nouns, but it can also consist of an adjective and a noun, an adverb and a noun, or a verb and a noun."},{"type":"table","table":[["de koffie + het kopje","het koffiekopje","the coffeecup"],["het werk + de plaats","de werkplaats","the workplace"],["het land + de bouw","de landbouw","the agriculture"]]},{"type":"table","table":[["klein + het geld","het kleingeld","small change"],["groot + de meester","de grootmeester","grand-master"],["rood + het borstje","het roodborstje","robin ('red chest')"]]},{"type":"table","table":[["voor + de loper","de voorloper","the precedent ('forerunner')"],["tegen + de speler","de tegenspeler","the adversary ('against player')"],["achter + de deur","de achterdeur","the back door"]]},{"type":"p","text":"We use the stem of the verb (see the stem of a verb):"},{"type":"table","table":[["eten + de kamer","de eetkamer","the dining room"],["denken + de wijze","de denkwijze","the vision, way of thinking"],["roeien + de boot","de roeiboot","the rowing boat"]]}]}